{"version": 0.6, "generator": "Overpass API 0.7.62.7 375dc00a", "osm3s": {"timestamp_osm_base": "2025-06-25T19:00:58Z", "copyright": "The data included in this document is from www.openstreetmap.org. The data is made available under ODbL."}, "elements": [{"type": "node", "id": 320562513, "lat": -4.605813, "lon": -43.9402799}, {"type": "node", "id": 320562520, "lat": -4.6244749, "lon": -43.9166549}, {"type": "node", "id": 320562561, "lat": -4.625205, "lon": -43.9156349}, {"type": "node", "id": 320562564, "lat": -4.625702, "lon": -43.9145269}, {"type": "node", "id": 320562568, "lat": -4.6259119, "lon": -43.913493}, {"type": "node", "id": 320562570, "lat": -4.625923, "lon": -43.9124279}, {"type": "node", "id": 320562574, "lat": -4.6236849, "lon": -43.889943}, {"type": "node", "id": 320562578, "lat": -4.623703, "lon": -43.8889129}, {"type": "node", "id": 320562583, "lat": -4.6238999, "lon": -43.887872}, {"type": "node", "id": 320562610, "lat": -4.6259549, "lon": -43.881473}, {"type": "node", "id": 320562649, "lat": -4.626637, "lon": -43.879643}, {"type": "node", "id": 320562652, "lat": -4.627153, "lon": -43.8787319}, {"type": "node", "id": 320562656, "lat": -4.62793, "lon": -43.877728}, {"type": "node", "id": 320562659, "lat": -4.6574799, "lon": -43.84612}, {"type": "node", "id": 320562662, "lat": -4.6591029, "lon": -43.8443449}, {"type": "node", "id": 320562665, "lat": -4.6598516, "lon": -43.843167}, {"type": "node", "id": 320562669, "lat": -4.6602701, "lon": -43.842301}, {"type": "node", "id": 320562672, "lat": -4.6623699, "lon": -43.836183}, {"type": "node", "id": 320562676, "lat": -4.6630479, "lon": -43.83476}, {"type": "node", "id": 320562678, "lat": -4.663833, "lon": -43.833652}, {"type": "node", "id": 320562687, "lat": -4.687833, "lon": -43.8058199}, {"type": "node", "id": 320562693, "lat": -4.697712, "lon": -43.794288}, {"type": "node", "id": 320562696, "lat": -4.6987399, "lon": -43.7930169}, {"type": "node", "id": 320562715, "lat": -4.6992719, "lon": -43.792093}, {"type": "node", "id": 320562718, "lat": -4.69975, "lon": -43.7908199}, {"type": "node", "id": 320562721, "lat": -4.702372, "lon": -43.7790246}, {"type": "node", "id": 320562724, "lat": -4.7028243, "lon": -43.7775308}, {"type": "node", "id": 320562727, "lat": -4.703485, "lon": -43.7764999}, {"type": "node", "id": 320562731, "lat": -4.71136, "lon": -43.7681699}, {"type": "node", "id": 320562733, "lat": -4.7122269, "lon": -43.7669479}, {"type": "node", "id": 320562737, "lat": -4.712627, "lon": -43.766045}, {"type": "node", "id": 320562740, "lat": -4.7153255, "lon": -43.7520132}, {"type": "node", "id": 320562744, "lat": -4.7159115, "lon": -43.7502066}, {"type": "node", "id": 320562748, "lat": -4.7220002, "lon": -43.7370816}, {"type": "node", "id": 320562786, "lat": -4.7225344, "lon": -43.7356181}, {"type": "node", "id": 320562788, "lat": -4.7272849, "lon": -43.7168569}, {"type": "node", "id": 320562789, "lat": -4.727692, "lon": -43.7155049}, {"type": "node", "id": 320562790, "lat": -4.728368, "lon": -43.7140829}, {"type": "node", "id": 320562792, "lat": -4.7443067, "lon": -43.6852049}, {"type": "node", "id": 320562812, "lat": -4.7450019, "lon": -43.683798}, {"type": "node", "id": 320562819, "lat": -4.74544, "lon": -43.6818707}, {"type": "node", "id": 320562824, "lat": -4.7472611, "lon": -43.6705703}, {"type": "node", "id": 320562829, "lat": -4.7476834, "lon": -43.6692709}, {"type": "node", "id": 320562834, "lat": -4.7480529, "lon": -43.6685079}, {"type": "node", "id": 320562840, "lat": -4.7683129, "lon": -43.6317769}, {"type": "node", "id": 320562842, "lat": -4.7687449, "lon": -43.6308729}, {"type": "node", "id": 320562845, "lat": -4.768915, "lon": -43.629875}, {"type": "node", "id": 320562847, "lat": -4.76628, "lon": -43.605427}, {"type": "node", "id": 320562855, "lat": -4.7662319, "lon": -43.604027}, {"type": "node", "id": 320562874, "lat": -4.766365, "lon": -43.6029419}, {"type": "node", "id": 320562877, "lat": -4.766728, "lon": -43.601695}, {"type": "node", "id": 320562881, "lat": -4.767302, "lon": -43.600505}, {"type": "node", "id": 320562907, "lat": -4.768053, "lon": -43.5994499}, {"type": "node", "id": 320562908, "lat": -4.771372, "lon": -43.596122}, {"type": "node", "id": 320562909, "lat": -4.7720829, "lon": -43.595555}, {"type": "node", "id": 320562910, "lat": -4.773038, "lon": -43.5950499}, {"type": "node", "id": 320562912, "lat": -4.7772149, "lon": -43.5937669}, {"type": "node", "id": 320562913, "lat": -4.778505, "lon": -43.5932079}, {"type": "node", "id": 320562914, "lat": -4.7792999, "lon": -43.592767}, {"type": "node", "id": 320562915, "lat": -4.785117, "lon": -43.5881869}, {"type": "node", "id": 320562916, "lat": -4.7862229, "lon": -43.587118}, {"type": "node", "id": 320562917, "lat": -4.7869379, "lon": -43.5861749}, {"type": "node", "id": 320562919, "lat": -4.7874704, "lon": -43.585117}, {"type": "node", "id": 320562920, "lat": -4.7878906, "lon": -43.5837614}, {"type": "node", "id": 320562923, "lat": -4.7886819, "lon": -43.578055}, {"type": "node", "id": 320562931, "lat": -4.7890229, "lon": -43.5766419}, {"type": "node", "id": 320562933, "lat": -4.78949, "lon": -43.5754449}, {"type": "node", "id": 320562934, "lat": -4.7955379, "lon": -43.565503}, {"type": "node", "id": 320562935, "lat": -4.79844, "lon": -43.5608479}, {"type": "node", "id": 320562936, "lat": -4.799202, "lon": -43.5598149}, {"type": "node", "id": 320562937, "lat": -4.8003999, "lon": -43.55863}, {"type": "node", "id": 320562939, "lat": -4.810777, "lon": -43.55021}, {"type": "node", "id": 320562943, "lat": -4.811942, "lon": -43.549117}, {"type": "node", "id": 320562945, "lat": -4.812845, "lon": -43.5479629}, {"type": "node", "id": 320562947, "lat": -4.813525, "lon": -43.5468429}, {"type": "node", "id": 320562949, "lat": -4.827398, "lon": -43.5177169}, {"type": "node", "id": 320562951, "lat": -4.8278699, "lon": -43.5165399}, {"type": "node", "id": 320562952, "lat": -4.8281419, "lon": -43.515297}, {"type": "node", "id": 320562954, "lat": -4.830622, "lon": -43.494002}, {"type": "node", "id": 320562964, "lat": -4.8308599, "lon": -43.492748}, {"type": "node", "id": 320562966, "lat": -4.8498089, "lon": -43.4510076}, {"type": "node", "id": 2366971046, "lat": -4.6275782, "lon": -43.4562267}, {"type": "node", "id": 2366971048, "lat": -4.6276102, "lon": -43.4544671}, {"type": "node", "id": 2366971060, "lat": -4.6290053, "lon": -43.452604}, {"type": "node", "id": 2366971070, "lat": -4.6318458, "lon": -43.4508047}, {"type": "node", "id": 2366971074, "lat": -4.6369607, "lon": -43.4476632}, {"type": "node", "id": 2366971078, "lat": -4.6396877, "lon": -43.4467263}, {"type": "node", "id": 2366971083, "lat": -4.6418951, "lon": -43.4454694}, {"type": "node", "id": 2366971087, "lat": -4.6438332, "lon": -43.444036}, {"type": "node", "id": 2366971091, "lat": -4.6476579, "lon": -43.4428081}, {"type": "node", "id": 2366971095, "lat": -4.6498066, "lon": -43.4424039}, {"type": "node", "id": 2366971097, "lat": -4.6520469, "lon": -43.4419473}, {"type": "node", "id": 2366971101, "lat": -4.6549186, "lon": -43.4413724}, {"type": "node", "id": 2366971103, "lat": -4.656235, "lon": -43.4399563}, {"type": "node", "id": 2366971107, "lat": -4.6571221, "lon": -43.439143}, {"type": "node", "id": 2366971109, "lat": -4.6597359, "lon": -43.4376298}, {"type": "node", "id": 2366971111, "lat": -4.6614208, "lon": -43.4362128}, {"type": "node", "id": 2366971115, "lat": -4.663448, "lon": -43.4357918}, {"type": "node", "id": 2366971117, "lat": -4.6649956, "lon": -43.4364719}, {"type": "node", "id": 2366971119, "lat": -4.6677666, "lon": -43.4372422}, {"type": "node", "id": 2366971123, "lat": -4.670234, "lon": -43.4375815}, {"type": "node", "id": 2366971125, "lat": -4.6730918, "lon": -43.4374388}, {"type": "node", "id": 2366971130, "lat": -4.675151, "lon": -43.4365368}, {"type": "node", "id": 2366971132, "lat": -4.6756144, "lon": -43.4360367}, {"type": "node", "id": 2366971134, "lat": -4.6767488, "lon": -43.4359593}, {"type": "node", "id": 2366971138, "lat": -4.6785237, "lon": -43.4364018}, {"type": "node", "id": 2366971144, "lat": -4.6848744, "lon": -43.435562}, {"type": "node", "id": 2366971148, "lat": -4.6883053, "lon": -43.4333235}, {"type": "node", "id": 2366971155, "lat": -4.6901067, "lon": -43.4325993}, {"type": "node", "id": 2366971157, "lat": -4.6926135, "lon": -43.4301029}, {"type": "node", "id": 2366971159, "lat": -4.6936983, "lon": -43.42747}, {"type": "node", "id": 2366971160, "lat": -4.6940203, "lon": -43.4269305}, {"type": "node", "id": 2366971162, "lat": -4.6958254, "lon": -43.4157859}, {"type": "node", "id": 2366971163, "lat": -4.6956922, "lon": -43.4139729}, {"type": "node", "id": 2366971164, "lat": -4.6963096, "lon": -43.4227101}, {"type": "node", "id": 2366971165, "lat": -4.6962063, "lon": -43.416225}, {"type": "node", "id": 2366971166, "lat": -4.6962082, "lon": -43.4123738}, {"type": "node", "id": 2366971167, "lat": -4.6976288, "lon": -43.4080471}, {"type": "node", "id": 2366971168, "lat": -4.6970033, "lon": -43.4172128}, {"type": "node", "id": 2366971169, "lat": -4.6972674, "lon": -43.4193523}, {"type": "node", "id": 2366971170, "lat": -4.7000127, "lon": -43.4044644}, {"type": "node", "id": 2366971172, "lat": -4.7032011, "lon": -43.4004483}, {"type": "node", "id": 2366971175, "lat": -4.7088938, "lon": -43.3937107}, {"type": "node", "id": 2366971176, "lat": -4.7095551, "lon": -43.3931796}, {"type": "node", "id": 2366971177, "lat": -4.7125471, "lon": -43.3917716}, {"type": "node", "id": 2366971179, "lat": -4.713871, "lon": -43.3904841}, {"type": "node", "id": 2366971180, "lat": -4.7174301, "lon": -43.3888824}, {"type": "node", "id": 2366971191, "lat": -4.723573, "lon": -43.3875604}, {"type": "node", "id": 2366971195, "lat": -4.7258344, "lon": -43.3872685}, {"type": "node", "id": 2366971197, "lat": -4.7285975, "lon": -43.3867775}, {"type": "node", "id": 2366971200, "lat": -4.7324585, "lon": -43.3874529}, {"type": "node", "id": 2366971202, "lat": -4.735551, "lon": -43.3892028}, {"type": "node", "id": 2366971208, "lat": -4.7383721, "lon": -43.3899318}, {"type": "node", "id": 2366971213, "lat": -4.7414532, "lon": -43.3907758}, {"type": "node", "id": 2366971217, "lat": -4.7436304, "lon": -43.391751}, {"type": "node", "id": 2366971219, "lat": -4.744936, "lon": -43.3926874}, {"type": "node", "id": 2366971221, "lat": -4.746868, "lon": -43.3939852}, {"type": "node", "id": 2366971223, "lat": -4.7487103, "lon": -43.3945188}, {"type": "node", "id": 2366971225, "lat": -4.7505681, "lon": -43.394577}, {"type": "node", "id": 2366971227, "lat": -4.7519277, "lon": -43.3942023}, {"type": "node", "id": 2366971243, "lat": -4.7577826, "lon": -43.3923031}, {"type": "node", "id": 2366971253, "lat": -4.7623414, "lon": -43.3900565}, {"type": "node", "id": 2366971257, "lat": -4.7634821, "lon": -43.388737}, {"type": "node", "id": 2366971261, "lat": -4.7638961, "lon": -43.3881733}, {"type": "node", "id": 2366971265, "lat": -4.7646477, "lon": -43.3861495}, {"type": "node", "id": 2366971269, "lat": -4.7649156, "lon": -43.3854565}, {"type": "node", "id": 2366971272, "lat": -4.7662529, "lon": -43.383364}, {"type": "node", "id": 2366971274, "lat": -4.7668709, "lon": -43.3830582}, {"type": "node", "id": 2366971284, "lat": -4.7763764, "lon": -43.3804128}, {"type": "node", "id": 2366971288, "lat": -4.7797827, "lon": -43.37954}, {"type": "node", "id": 2366971290, "lat": -4.7808641, "lon": -43.3788306}, {"type": "node", "id": 2366971292, "lat": -4.7848073, "lon": -43.3744478}, {"type": "node", "id": 2366971298, "lat": -4.7899777, "lon": -43.3680363}, {"type": "node", "id": 2366971300, "lat": -4.7906096, "lon": -43.3669699}, {"type": "node", "id": 2366971302, "lat": -4.7920751, "lon": -43.3637699}, {"type": "node", "id": 2366971310, "lat": -4.793415, "lon": -43.3607623}, {"type": "node", "id": 2366971312, "lat": -4.7940167, "lon": -43.3543008}, {"type": "node", "id": 2366971314, "lat": -4.7940167, "lon": -43.3551601}, {"type": "node", "id": 2366971316, "lat": -4.7945841, "lon": -43.3535532}, {"type": "node", "id": 2366971318, "lat": -4.7948004, "lon": -43.358437}, {"type": "node", "id": 2366971320, "lat": -4.7948018, "lon": -43.3574977}, {"type": "node", "id": 2366971324, "lat": -4.7960227, "lon": -43.3522909}, {"type": "node", "id": 2366971326, "lat": -4.7962807, "lon": -43.3514608}, {"type": "node", "id": 2366971328, "lat": -4.7964191, "lon": -43.3488447}, {"type": "node", "id": 2366971330, "lat": -4.7974272, "lon": -43.344469}, {"type": "node", "id": 2366971334, "lat": -4.7979052, "lon": -43.3437793}, {"type": "node", "id": 2366971338, "lat": -4.7993174, "lon": -43.3429718}, {"type": "node", "id": 2366971342, "lat": -4.8008588, "lon": -43.3421173}, {"type": "node", "id": 3895156629, "lat": -4.7864042, "lon": -43.3725759}, {"type": "node", "id": 4729818702, "lat": -4.6644328, "lon": -43.4362671}, {"type": "node", "id": 4729818703, "lat": -4.6623253, "lon": -43.4358734}, {"type": "node", "id": 4729818704, "lat": -4.6627897, "lon": -43.4357483}, {"type": "node", "id": 4729818705, "lat": -4.6631029, "lon": -43.435759}, {"type": "node", "id": 4729818706, "lat": -4.6606423, "lon": -43.4367625}, {"type": "node", "id": 4729818707, "lat": -4.6609503, "lon": -43.4364893}, {"type": "node", "id": 4729818708, "lat": -4.6576507, "lon": -43.4387214}, {"type": "node", "id": 4729818709, "lat": -4.6579938, "lon": -43.438514}, {"type": "node", "id": 4729818710, "lat": -4.6588416, "lon": -43.4382343}, {"type": "node", "id": 4729818711, "lat": -4.6591839, "lon": -43.4381005}, {"type": "node", "id": 4729818712, "lat": -4.6594416, "lon": -43.4379275}, {"type": "node", "id": 4729818713, "lat": -4.6556149, "lon": -43.4406241}, {"type": "node", "id": 4729818714, "lat": -4.654594, "lon": -43.4416515}, {"type": "node", "id": 4729818715, "lat": -4.6542315, "lon": -43.4417649}, {"type": "node", "id": 4729818716, "lat": -4.653836, "lon": -43.4417951}, {"type": "node", "id": 4729818717, "lat": -4.652828, "lon": -43.4418427}, {"type": "node", "id": 4729818718, "lat": -4.6532834, "lon": -43.4417864}, {"type": "node", "id": 4729818719, "lat": -4.6530557, "lon": -43.4418064}, {"type": "node", "id": 4729818720, "lat": -4.6467714, "lon": -43.4430186}, {"type": "node", "id": 4729818721, "lat": -4.6472146, "lon": -43.442889}, {"type": "node", "id": 4729818722, "lat": -4.6427669, "lon": -43.4446795}, {"type": "node", "id": 4729818723, "lat": -4.6432109, "lon": -43.4443415}, {"type": "node", "id": 4729818724, "lat": -4.6435301, "lon": -43.4441644}, {"type": "node", "id": 4729818725, "lat": -4.6453671, "lon": -43.4434704}, {"type": "node", "id": 4729818726, "lat": -4.6413464, "lon": -43.4458499}, {"type": "node", "id": 4729818727, "lat": -4.6404522, "lon": -43.4464182}, {"type": "node", "id": 4729818728, "lat": -4.64007, "lon": -43.4465966}, {"type": "node", "id": 4729818729, "lat": -4.6383404, "lon": -43.4470322}, {"type": "node", "id": 4729818730, "lat": -4.6376586, "lon": -43.4472827}, {"type": "node", "id": 4729818731, "lat": -4.6379995, "lon": -43.447133}, {"type": "node", "id": 4729818732, "lat": -4.6282352, "lon": -43.4533337}, {"type": "node", "id": 4729818733, "lat": -4.6277854, "lon": -43.4540213}, {"type": "node", "id": 4729818734, "lat": -4.6274471, "lon": -43.4554978}, {"type": "node", "id": 4729818735, "lat": -4.6274854, "lon": -43.4549139}, {"type": "node", "id": 4729818740, "lat": -4.6274802, "lon": -43.4557836}, {"type": "node", "id": 4729818741, "lat": -4.6274487, "lon": -43.4551803}, {"type": "node", "id": 4729818742, "lat": -4.6279822, "lon": -43.4536773}, {"type": "node", "id": 5312747101, "lat": -4.6352731, "lon": -43.8698736}, {"type": "node", "id": 5312747334, "lat": -4.7473633, "lon": -43.6701822}, {"type": "node", "id": 5312747379, "lat": -4.7688753, "lon": -43.6295069}, {"type": "node", "id": 5312747504, "lat": -4.6257565, "lon": -43.9107548}, {"type": "node", "id": 5312747547, "lat": -4.6122264, "lon": -43.9321609}, {"type": "node", "id": 5312747788, "lat": -4.6846604, "lon": -43.8094991}, {"type": "node", "id": 5312747917, "lat": -4.8089489, "lon": -43.5516933}, {"type": "node", "id": 5312748055, "lat": -4.7688377, "lon": -43.6291575}, {"type": "node", "id": 5404439712, "lat": -4.7909695, "lon": -43.3661522}, {"type": "node", "id": 5644132473, "lat": -4.609174, "lon": -43.9360251}, {"type": "node", "id": 5644132479, "lat": -4.6192614, "lon": -43.923255}, {"type": "node", "id": 5644132486, "lat": -4.6184758, "lon": -43.9242495}, {"type": "node", "id": 5644132490, "lat": -4.6246942, "lon": -43.9000827}, {"type": "node", "id": 5644132518, "lat": -4.6364184, "lon": -43.8686486}, {"type": "node", "id": 5644132659, "lat": -4.6444778, "lon": -43.8600279}, {"type": "node", "id": 5644132663, "lat": -4.6480718, "lon": -43.8561835}, {"type": "node", "id": 5644132665, "lat": -4.6475314, "lon": -43.8567615}, {"type": "node", "id": 5644132668, "lat": -4.655393, "lon": -43.8483523}, {"type": "node", "id": 5644132677, "lat": -4.6564471, "lon": -43.8472248}, {"type": "node", "id": 5644132680, "lat": -4.6573279, "lon": -43.8462826}, {"type": "node", "id": 5644132682, "lat": -4.6612392, "lon": -43.839443}, {"type": "node", "id": 5644132685, "lat": -4.6808712, "lon": -43.8138934}, {"type": "node", "id": 5644132702, "lat": -4.6898306, "lon": -43.803488}, {"type": "node", "id": 5644132717, "lat": -4.7126819, "lon": -43.7657656}, {"type": "node", "id": 5644133031, "lat": -4.712877, "lon": -43.7647733}, {"type": "node", "id": 5644133050, "lat": -4.7945223, "lon": -43.5671725}, {"type": "node", "id": 5644133051, "lat": -4.8187066, "lon": -43.5359644}, {"type": "node", "id": 5644133053, "lat": -4.8220592, "lon": -43.5289256}, {"type": "node", "id": 5644133055, "lat": -4.8240682, "lon": -43.5247079}, {"type": "node", "id": 5644133059, "lat": -4.8248345, "lon": -43.5230989}, {"type": "node", "id": 5644133078, "lat": -4.8284849, "lon": -43.5123517}, {"type": "node", "id": 5644133089, "lat": -4.8303279, "lon": -43.496527}, {"type": "node", "id": 5644133094, "lat": -4.8337132, "lon": -43.4864651}, {"type": "node", "id": 5644133258, "lat": -4.8415874, "lon": -43.4691116}, {"type": "node", "id": 5644133262, "lat": -4.8450939, "lon": -43.4613902}, {"type": "node", "id": 5644133282, "lat": -4.8477496, "lon": -43.4555422}, {"type": "node", "id": 5728551126, "lat": -4.8385236, "lon": -43.4758583}, {"type": "node", "id": 5735268491, "lat": -4.6301608, "lon": -43.451837}, {"type": "node", "id": 5735268492, "lat": -4.6285914, "lon": -43.4529528}, {"type": "node", "id": 5815122591, "lat": -4.6236571, "lon": -43.8894353}, {"type": "node", "id": 5815122606, "lat": -4.7565279, "lon": -43.653143}, {"type": "node", "id": 5815122609, "lat": -4.7560841, "lon": -43.6539477}, {"type": "node", "id": 5815122610, "lat": -4.7614604, "lon": -43.6442005}, {"type": "node", "id": 5815122611, "lat": -4.7619593, "lon": -43.643296}, {"type": "node", "id": 5815122614, "lat": -4.7689223, "lon": -43.630374}, {"type": "node", "id": 5815122615, "lat": -4.7672285, "lon": -43.6142275}, {"type": "node", "id": 5815122628, "lat": -4.8344467, "lon": -43.4847673}, {"type": "node", "id": 5815122629, "lat": -4.8340223, "lon": -43.485736}, {"type": "node", "id": 5815122636, "lat": -4.8374144, "lon": -43.4782823}, {"type": "node", "id": 5815122639, "lat": -4.8380195, "lon": -43.4769598}, {"type": "node", "id": 5815126889, "lat": -4.8565117, "lon": -43.4363856}, {"type": "node", "id": 5815126900, "lat": -4.8600053, "lon": -43.4288462}, {"type": "node", "id": 5872225189, "lat": -4.7127026, "lon": -43.7656605}, {"type": "node", "id": 5872225196, "lat": -4.7128669, "lon": -43.7648245}, {"type": "node", "id": 5872225197, "lat": -4.7127766, "lon": -43.765284}, {"type": "node", "id": 5872225198, "lat": -4.7127873, "lon": -43.7652298}, {"type": "node", "id": 6168913903, "lat": -4.7571343, "lon": -43.6521149}, {"type": "node", "id": 6248332674, "lat": -4.6566276, "lon": -43.4395695}, {"type": "node", "id": 6248332676, "lat": -4.6583454, "lon": -43.4383703}, {"type": "node", "id": 6248346364, "lat": -4.8312786, "lon": -43.4917163}, {"type": "node", "id": 6374478634, "lat": -4.7975679, "lon": -43.3440749}, {"type": "node", "id": 6374478636, "lat": -4.7962008, "lon": -43.3519498}, {"type": "node", "id": 6374478637, "lat": -4.794239, "lon": -43.3538654}, {"type": "node", "id": 6374478638, "lat": -4.7939307, "lon": -43.3546935}, {"type": "node", "id": 6374478639, "lat": -4.7948625, "lon": -43.3579674}, {"type": "node", "id": 6374478640, "lat": -4.7946277, "lon": -43.358768}, {"type": "node", "id": 6374478641, "lat": -4.7938047, "lon": -43.3600571}, {"type": "node", "id": 6374478642, "lat": -4.7903257, "lon": -43.3675492}, {"type": "node", "id": 6374478643, "lat": -4.7802032, "lon": -43.3793166}, {"type": "node", "id": 6374478644, "lat": -4.7805016, "lon": -43.3791743}, {"type": "node", "id": 6374478645, "lat": -4.7651368, "lon": -43.3847232}, {"type": "node", "id": 6374478646, "lat": -4.7654107, "lon": -43.384234}, {"type": "node", "id": 6374478647, "lat": -4.7658077, "lon": -43.3837192}, {"type": "node", "id": 6374478648, "lat": -4.7642377, "lon": -43.3876279}, {"type": "node", "id": 6374478649, "lat": -4.7617074, "lon": -43.3905816}, {"type": "node", "id": 6374478650, "lat": -4.7610094, "lon": -43.3909893}, {"type": "node", "id": 6374478651, "lat": -4.7510714, "lon": -43.3944736}, {"type": "node", "id": 6374478652, "lat": -4.7497971, "lon": -43.3946132}, {"type": "node", "id": 6374478653, "lat": -4.7492723, "lon": -43.3945846}, {"type": "node", "id": 6374478654, "lat": -4.7479843, "lon": -43.3943639}, {"type": "node", "id": 6374478655, "lat": -4.7474261, "lon": -43.3942118}, {"type": "node", "id": 6374478656, "lat": -4.7432492, "lon": -43.3915019}, {"type": "node", "id": 6374478657, "lat": -4.7428095, "lon": -43.3912857}, {"type": "node", "id": 6374478658, "lat": -4.7407635, "lon": -43.3905175}, {"type": "node", "id": 6374478659, "lat": -4.7401375, "lon": -43.3903313}, {"type": "node", "id": 6374478660, "lat": -4.7352551, "lon": -43.3891142}, {"type": "node", "id": 6374478661, "lat": -4.7347439, "lon": -43.3889115}, {"type": "node", "id": 6374478662, "lat": -4.7313654, "lon": -43.3870439}, {"type": "node", "id": 6374478663, "lat": -4.7320617, "lon": -43.3873059}, {"type": "node", "id": 6374478664, "lat": -4.7317322, "lon": -43.3871563}, {"type": "node", "id": 6374478665, "lat": -4.7271899, "lon": -43.3868385}, {"type": "node", "id": 6374478666, "lat": -4.7276986, "lon": -43.386752}, {"type": "node", "id": 6374478667, "lat": -4.7281573, "lon": -43.3867554}, {"type": "node", "id": 6374478668, "lat": -4.7254006, "lon": -43.3873941}, {"type": "node", "id": 6374478669, "lat": -4.7249632, "lon": -43.3874628}, {"type": "node", "id": 6374478670, "lat": -4.7231038, "lon": -43.3876054}, {"type": "node", "id": 6374478671, "lat": -4.722643, "lon": -43.3876667}, {"type": "node", "id": 6374478672, "lat": -4.7166276, "lon": -43.3890954}, {"type": "node", "id": 6374478673, "lat": -4.7156201, "lon": -43.3894835}, {"type": "node", "id": 6374478674, "lat": -4.7147205, "lon": -43.3898674}, {"type": "node", "id": 6374478675, "lat": -4.7120561, "lon": -43.3920737}, {"type": "node", "id": 6374478676, "lat": -4.7092802, "lon": -43.3933519}, {"type": "node", "id": 6374478677, "lat": -4.698059, "lon": -43.4070874}, {"type": "node", "id": 6374478678, "lat": -4.6985869, "lon": -43.4062079}, {"type": "node", "id": 6374478679, "lat": -4.6955031, "lon": -43.4151376}, {"type": "node", "id": 6374478680, "lat": -4.6955028, "lon": -43.4146725}, {"type": "node", "id": 6374478681, "lat": -4.6967163, "lon": -43.4168028}, {"type": "node", "id": 6374478682, "lat": -4.6973803, "lon": -43.4186719}, {"type": "node", "id": 6374478683, "lat": -4.6973136, "lon": -43.4181173}, {"type": "node", "id": 6374478684, "lat": -4.6971674, "lon": -43.4176157}, {"type": "node", "id": 6374479185, "lat": -4.6959925, "lon": -43.4236497}, {"type": "node", "id": 6374479186, "lat": -4.6954314, "lon": -43.4250417}, {"type": "node", "id": 6374479187, "lat": -4.6950567, "lon": -43.4256212}, {"type": "node", "id": 6374479188, "lat": -4.6933655, "lon": -43.4281733}, {"type": "node", "id": 6374479189, "lat": -4.6922355, "lon": -43.4308254}, {"type": "node", "id": 6374479190, "lat": -4.6919145, "lon": -43.4312844}, {"type": "node", "id": 6374479191, "lat": -4.6915286, "lon": -43.4316129}, {"type": "node", "id": 6374479192, "lat": -4.6897239, "lon": -43.4328661}, {"type": "node", "id": 6374479193, "lat": -4.6876804, "lon": -43.4336157}, {"type": "node", "id": 6374479194, "lat": -4.6838656, "lon": -43.4359771}, {"type": "node", "id": 6374479195, "lat": -4.6843514, "lon": -43.4358535}, {"type": "node", "id": 6374479196, "lat": -4.6780544, "lon": -43.4364043}, {"type": "node", "id": 6374479197, "lat": -4.6775305, "lon": -43.4362806}, {"type": "node", "id": 6374479198, "lat": -4.6759214, "lon": -43.4358768}, {"type": "node", "id": 6374479199, "lat": -4.6762794, "lon": -43.4358714}, {"type": "node", "id": 6374479200, "lat": -4.6748457, "lon": -43.436876}, {"type": "node", "id": 6374479201, "lat": -4.6745002, "lon": -43.4370727}, {"type": "node", "id": 6374479202, "lat": -4.6727536, "lon": -43.4375145}, {"type": "node", "id": 6374479203, "lat": -4.6713358, "lon": -43.4374451}, {"type": "node", "id": 6374479204, "lat": -4.6725464, "lon": -43.4375359}, {"type": "node", "id": 6374479205, "lat": -4.6717181, "lon": -43.4374813}, {"type": "node", "id": 6374479206, "lat": -4.6699341, "lon": -43.4375843}, {"type": "node", "id": 6374479207, "lat": -4.6696291, "lon": -43.4375496}, {"type": "node", "id": 6374479208, "lat": -4.6673108, "lon": -43.4371421}, {"type": "node", "id": 6374479209, "lat": -4.6611503, "lon": -43.4363511}, {"type": "node", "id": 6374479210, "lat": -4.6547492, "lon": -43.4415473}, {"type": "node", "id": 7018618253, "lat": -4.8580502, "lon": -43.4330642}, {"type": "node", "id": 7613716886, "lat": -4.747096, "lon": -43.6713704}, {"type": "node", "id": 8756188937, "lat": -4.7543915, "lon": -43.3934031}, {"type": "node", "id": 8756189633, "lat": -4.7645498, "lon": -43.3866261}, {"type": "node", "id": 8756190128, "lat": -4.7104567, "lon": -43.3927809}, {"type": "node", "id": 8756193919, "lat": -4.696289, "lon": -43.4121526}, {"type": "node", "id": 8756235072, "lat": -4.8566152, "lon": -43.4362404}, {"type": "node", "id": 8756235316, "lat": -4.7969065, "lon": -43.3467291}, {"type": "node", "id": 9136158292, "lat": -4.6604282, "lon": -43.8418978}, {"type": "node", "id": 10605195223, "lat": -4.6907948, "lon": -43.4321523}, {"type": "node", "id": 10605195224, "lat": -4.6929601, "lon": -43.4292448}, {"type": "node", "id": 10605195225, "lat": -4.6956119, "lon": -43.4155655}, {"type": "node", "id": 10605195226, "lat": -4.6991726, "lon": -43.4054267}, {"type": "node", "id": 10605195227, "lat": -4.7201622, "lon": -43.3881909}, {"type": "node", "id": 10605195228, "lat": -4.714292, "lon": -43.3901435}, {"type": "node", "id": 10605195229, "lat": -4.7336613, "lon": -43.3883303}, {"type": "node", "id": 10605195230, "lat": -4.7392694, "lon": -43.3900952}, {"type": "node", "id": 10605195231, "lat": -4.7458878, "lon": -43.3934265}, {"type": "node", "id": 10605195346, "lat": -4.74634, "lon": -43.676249}, {"type": "node", "id": 10605269242, "lat": -4.7737507, "lon": -43.3811791}, {"type": "node", "id": 10605321177, "lat": -4.7367591, "lon": -43.389515}, {"type": "node", "id": 11278568190, "lat": -4.745265, "lon": -43.682735}, {"type": "node", "id": 11278568191, "lat": -4.7223408, "lon": -43.7363523}, {"type": "node", "id": 11278568192, "lat": -4.7155698, "lon": -43.7510669}, {"type": "node", "id": 11278568193, "lat": -4.7025515, "lon": -43.7782109}, {"type": "node", "id": 11278568194, "lat": -4.7031396, "lon": -43.7770522}, {"type": "node", "id": 12095176733, "lat": -4.7568005, "lon": -43.6526904}, {"type": "way", "id": 29144365, "nodes": [320562513, 5644132473, 5312747547, 5644132486, 5644132479, 320562520, 320562561, 320562564, 320562568, 320562570, 5312747504, 5644132490, 320562574, 5815122591, 320562578, 320562583, 320562610, 320562649, 320562652, 320562656, 5312747101, 5644132518, 5644132659, 5644132665, 5644132663, 5644132668, 5644132677, 5644132680, 320562659, 320562662, 320562665, 320562669, 9136158292, 5644132682, 320562672, 320562676, 320562678, 5644132685, 5312747788, 320562687, 5644132702, 320562693, 320562696, 320562715, 320562718, 320562721, 11278568193, 320562724, 11278568194, 320562727, 320562731, 320562733, 320562737, 5644132717, 5872225189, 5872225197, 5872225198, 5872225196, 5644133031, 320562740, 11278568192, 320562744, 320562748, 11278568191, 320562786, 320562788, 320562789, 320562790, 320562792, 320562812, 11278568190, 320562819, 10605195346, 7613716886, 320562824, 5312747334, 320562829, 320562834, 5815122609, 5815122606, 12095176733, 6168913903, 5815122610], "tags": {"highway": "trunk", "lanes": "2", "maxspeed": "80", "ref": "BR-316", "surface": "paved"}}, {"type": "way", "id": 228045602, "nodes": [2366971342, 2366971338, 2366971334, 6374478634, 2366971330, 8756235316, 2366971328, 2366971326, 6374478636, 2366971324, 2366971316, 6374478637, 2366971312, 6374478638, 2366971314, 2366971320, 6374478639, 2366971318, 6374478640, 6374478641, 2366971310, 2366971302, 5404439712, 2366971300, 6374478642, 2366971298, 3895156629, 2366971292, 2366971290, 6374478644, 6374478643, 2366971288, 2366971284, 10605269242, 2366971274, 2366971272, 6374478647, 6374478646, 6374478645, 2366971269, 2366971265, 8756189633, 6374478648, 2366971261, 2366971257, 2366971253, 6374478649, 6374478650, 2366971243, 8756188937, 2366971227, 6374478651, 2366971225, 6374478652, 6374478653, 2366971223, 6374478654, 6374478655, 2366971221, 10605195231, 2366971219, 2366971217, 6374478656, 6374478657, 2366971213, 6374478658, 6374478659, 10605195230, 2366971208, 10605321177, 2366971202, 6374478660, 6374478661, 10605195229, 2366971200, 6374478663, 6374478664, 6374478662, 2366971197, 6374478667, 6374478666, 6374478665, 2366971195, 6374478668, 6374478669, 2366971191, 6374478670, 6374478671, 10605195227, 2366971180, 6374478672, 6374478673, 6374478674, 10605195228, 2366971179, 2366971177, 6374478675, 8756190128, 2366971176, 6374478676, 2366971175, 2366971172, 2366971170, 10605195226, 6374478678, 6374478677, 2366971167, 8756193919, 2366971166, 2366971163, 6374478680, 6374478679, 10605195225, 2366971162, 2366971165, 6374478681, 2366971168, 6374478684, 6374478683, 6374478682, 2366971169, 2366971164, 6374479185, 6374479186, 6374479187, 2366971160, 2366971159, 6374479188, 10605195224, 2366971157, 6374479189, 6374479190, 6374479191, 10605195223, 2366971155, 6374479192, 2366971148, 6374479193, 2366971144, 6374479195, 6374479194, 2366971138, 6374479196, 6374479197, 2366971134, 6374479199, 6374479198, 2366971132, 2366971130, 6374479200, 6374479201, 2366971125, 6374479202, 6374479204, 6374479205, 6374479203, 2366971123, 6374479206, 6374479207, 2366971119, 6374479208, 2366971117, 4729818702, 2366971115, 4729818705, 4729818704, 4729818703, 2366971111, 6374479209, 4729818707, 4729818706, 2366971109, 4729818712, 4729818711, 4729818710, 6248332676, 4729818709, 4729818708, 2366971107, 6248332674, 2366971103, 4729818713, 2366971101, 6374479210, 4729818714, 4729818715, 4729818716, 4729818718, 4729818719, 4729818717, 2366971097, 2366971095, 2366971091, 4729818721, 4729818720, 4729818725, 2366971087, 4729818724, 4729818723, 4729818722, 2366971083, 4729818726, 4729818727, 4729818728, 2366971078, 4729818729, 4729818731, 4729818730, 2366971074, 2366971070, 5735268491, 2366971060, 5735268492, 4729818732, 4729818742, 4729818733, 2366971048, 4729818735, 4729818741, 4729818734, 4729818740, 2366971046], "tags": {"highway": "primary", "lanes": "2", "name": "MA-349", "ref": "MA-349", "source": "IBGE", "surface": "asphalt"}}, {"type": "way", "id": 614840938, "nodes": [5815122610, 5815122611], "tags": {"bridge": "yes", "highway": "trunk", "lanes": "2", "layer": "1", "maxspeed": "80", "ref": "BR-316", "surface": "paved"}}, {"type": "way", "id": 614840939, "nodes": [5815122611, 320562840, 320562842, 5815122614, 320562845, 5312747379, 5312748055, 5815122615, 320562847, 320562855, 320562874, 320562877, 320562881, 320562907, 320562908, 320562909, 320562910, 320562912, 320562913, 320562914, 320562915, 320562916, 320562917, 320562919, 320562920, 320562923, 320562931, 320562933, 5644133050, 320562934, 320562935, 320562936, 320562937, 5312747917, 320562939, 320562943, 320562945, 320562947, 5644133051, 5644133053, 5644133055, 5644133059, 320562949, 320562951, 320562952, 5644133078, 5644133089, 320562954, 320562964, 6248346364, 5644133094, 5815122629], "tags": {"highway": "trunk", "lanes": "2", "maxspeed": "100", "ref": "BR-316", "surface": "paved"}}, {"type": "way", "id": 614840942, "nodes": [5815122629, 5815122628], "tags": {"bridge": "yes", "highway": "trunk", "lanes": "2", "layer": "1", "maxspeed": "100", "ref": "BR-316", "surface": "paved"}}, {"type": "way", "id": 614840943, "nodes": [5644133258, 5644133262, 5644133282, 320562966, 5815126889, 8756235072, 7018618253, 5815126900], "tags": {"highway": "trunk", "lanes": "2", "maxspeed": "100", "ref": "BR-316", "surface": "paved"}}, {"type": "way", "id": 1134476575, "nodes": [5728551126, 5644133258], "tags": {"highway": "trunk", "lanes": "2", "maxspeed": "100", "ref": "BR-316", "surface": "paved"}}, {"type": "way", "id": 1134476576, "nodes": [5815122639, 5728551126], "tags": {"highway": "trunk", "lanes": "2", "maxspeed": "100", "ref": "BR-316", "surface": "paved"}}, {"type": "way", "id": 1134476577, "nodes": [5815122628, 5815122636, 5815122639], "tags": {"highway": "trunk", "lanes": "2", "maxspeed": "100", "ref": "BR-316", "surface": "paved"}}]}