{"version": 0.6, "generator": "Overpass API 0.7.62.7 375dc00a", "osm3s": {"timestamp_osm_base": "2025-06-25T19:33:42Z", "copyright": "The data included in this document is from www.openstreetmap.org. The data is made available under ODbL."}, "elements": [{"type": "node", "id": 353133289, "lat": -14.244785, "lon": -43.1041906, "tags": {"source": "IBGE"}}, {"type": "node", "id": 353133292, "lat": -14.2452009, "lon": -43.1094304, "tags": {"source": "IBGE"}}, {"type": "node", "id": 353133293, "lat": -14.2455228, "lon": -43.1125698, "tags": {"source": "IBGE"}}, {"type": "node", "id": 353133294, "lat": -14.2474024, "lon": -43.1363127, "tags": {"source": "IBGE"}}, {"type": "node", "id": 353133295, "lat": -14.2466498, "lon": -43.1265628, "tags": {"source": "IBGE"}}, {"type": "node", "id": 353133296, "lat": -14.248129, "lon": -43.1455985, "tags": {"source": "IBGE"}}, {"type": "node", "id": 353133297, "lat": -14.2480614, "lon": -43.1446704, "tags": {"source": "IBGE"}}, {"type": "node", "id": 353133300, "lat": -14.2491387, "lon": -43.1581207, "tags": {"source": "IBGE"}}, {"type": "node", "id": 353133301, "lat": -14.2569736, "lon": -43.2548467, "tags": {"source": "IBGE"}}, {"type": "node", "id": 353133302, "lat": -14.2506157, "lon": -43.1769208, "tags": {"source": "IBGE"}}, {"type": "node", "id": 353133308, "lat": -14.2707966, "lon": -43.4206887}, {"type": "node", "id": 353133309, "lat": -14.2664536, "lon": -43.3692169, "tags": {"source": "IBGE"}}, {"type": "node", "id": 353133310, "lat": -14.2647418, "lon": -43.3486471, "tags": {"source": "IBGE"}}, {"type": "node", "id": 353133312, "lat": -14.2785114, "lon": -43.5116021}, {"type": "node", "id": 353133313, "lat": -14.2757764, "lon": -43.4790678}, {"type": "node", "id": 353133456, "lat": -14.246074, "lon": -43.1195059, "tags": {"source": "IBGE"}}, {"type": "node", "id": 1832311426, "lat": -14.2412615, "lon": -43.0600087}, {"type": "node", "id": 1832311427, "lat": -14.2542863, "lon": -43.222474}, {"type": "node", "id": 1832311428, "lat": -14.280807, "lon": -43.5385133}, {"type": "node", "id": 2389639962, "lat": -14.2501686, "lon": -43.1706855}, {"type": "node", "id": 2389642687, "lat": -14.250305, "lon": -43.1726291}, {"type": "node", "id": 2389644883, "lat": -14.2502534, "lon": -43.1719381}, {"type": "node", "id": 2389811650, "lat": -14.2504309, "lon": -43.1744806}, {"type": "node", "id": 2389814815, "lat": -14.2498728, "lon": -43.1672578}, {"type": "node", "id": 2389842672, "lat": -14.2493886, "lon": -43.1611942}, {"type": "node", "id": 3422098996, "lat": -14.269898, "lon": -43.410156}, {"type": "node", "id": 3422098997, "lat": -14.2701608, "lon": -43.4134341}, {"type": "node", "id": 3422099004, "lat": -14.2774167, "lon": -43.4983746}, {"type": "node", "id": 3843059959, "lat": -14.2608412, "lon": -43.3017084}, {"type": "node", "id": 3898730499, "lat": -14.2719997, "lon": -43.4346906}, {"type": "node", "id": 3898730500, "lat": -14.2732224, "lon": -43.4490134}, {"type": "node", "id": 3898730501, "lat": -14.2765963, "lon": -43.488689}, {"type": "node", "id": 3898730502, "lat": -14.2794934, "lon": -43.5226696}, {"type": "node", "id": 3898730503, "lat": -14.2815377, "lon": -43.5471026}, {"type": "node", "id": 3898730504, "lat": -14.2821846, "lon": -43.5549103}, {"type": "node", "id": 4279268546, "lat": -14.2602206, "lon": -43.2942941}, {"type": "node", "id": 4347894225, "lat": -14.272486, "lon": -43.4408709}, {"type": "node", "id": 4347911896, "lat": -14.2724691, "lon": -43.44065}, {"type": "node", "id": 4755001550, "lat": -14.2401336, "lon": -43.0457812}, {"type": "node", "id": 4755001612, "lat": -14.2417201, "lon": -43.065759}, {"type": "node", "id": 4755001613, "lat": -14.2416868, "lon": -43.0653422}, {"type": "node", "id": 4755001627, "lat": -14.2404622, "lon": -43.0499257}, {"type": "node", "id": 4755001628, "lat": -14.2405025, "lon": -43.050434}, {"type": "node", "id": 4755001658, "lat": -14.2402999, "lon": -43.0478788}, {"type": "node", "id": 5421685911, "lat": -14.2514618, "lon": -43.1834686}, {"type": "node", "id": 5421685914, "lat": -14.2511993, "lon": -43.183537}, {"type": "node", "id": 5421685915, "lat": -14.251196, "lon": -43.1834757}, {"type": "node", "id": 5421685930, "lat": -14.2513923, "lon": -43.183364}, {"type": "node", "id": 5421685931, "lat": -14.2513104, "lon": -43.1832969}, {"type": "node", "id": 5421685932, "lat": -14.251237, "lon": -43.1832198}, {"type": "node", "id": 5421685939, "lat": -14.2510618, "lon": -43.1817762}, {"type": "node", "id": 5421685941, "lat": -14.2513448, "lon": -43.1836047}, {"type": "node", "id": 5421685942, "lat": -14.2512773, "lon": -43.1837147}, {"type": "node", "id": 5421685947, "lat": -14.2513157, "lon": -43.1850083}, {"type": "node", "id": 5586095826, "lat": -14.251556, "lon": -43.188039}, {"type": "node", "id": 5586095904, "lat": -14.2504541, "lon": -43.1747872}, {"type": "node", "id": 5586095905, "lat": -14.2507632, "lon": -43.1785259}, {"type": "node", "id": 5602264289, "lat": -14.2500214, "lon": -43.1690769}, {"type": "node", "id": 5607510568, "lat": -14.2471606, "lon": -43.1334548}, {"type": "node", "id": 5607510590, "lat": -14.2470424, "lon": -43.131938}, {"type": "node", "id": 5607510593, "lat": -14.247019, "lon": -43.1315893}, {"type": "node", "id": 5607510601, "lat": -14.2469488, "lon": -43.1306693}, {"type": "node", "id": 5607512530, "lat": -14.2469098, "lon": -43.1302777}, {"type": "node", "id": 5622142129, "lat": -14.2482343, "lon": -43.146721}, {"type": "node", "id": 6026120392, "lat": -14.2511687, "lon": -43.1831387}, {"type": "node", "id": 6026120393, "lat": -14.2512211, "lon": -43.1839007}, {"type": "node", "id": 7058120457, "lat": -14.2601959, "lon": -43.2939139}, {"type": "node", "id": 7284051913, "lat": -14.2469267, "lon": -43.130444}, {"type": "node", "id": 7413895563, "lat": -14.2467807, "lon": -43.1286451}, {"type": "node", "id": 7413895580, "lat": -14.2473082, "lon": -43.1351986}, {"type": "node", "id": 7413895583, "lat": -14.2472873, "lon": -43.1349516}, {"type": "node", "id": 7413895584, "lat": -14.2474204, "lon": -43.1365437}, {"type": "node", "id": 7413900023, "lat": -14.247545, "lon": -43.1381502}, {"type": "node", "id": 7413900024, "lat": -14.2456996, "lon": -43.1146807}, {"type": "node", "id": 7413900025, "lat": -14.2458998, "lon": -43.1172207}, {"type": "node", "id": 7413900026, "lat": -14.2463885, "lon": -43.123261}, {"type": "node", "id": 7413900027, "lat": -14.2466771, "lon": -43.1270228}, {"type": "node", "id": 7413900028, "lat": -14.2467018, "lon": -43.1275982}, {"type": "node", "id": 7413900029, "lat": -14.2468292, "lon": -43.129288}, {"type": "node", "id": 7413900030, "lat": -14.2476052, "lon": -43.1389251}, {"type": "node", "id": 7413900031, "lat": -14.247821, "lon": -43.1415886}, {"type": "node", "id": 7413931779, "lat": -14.2456845, "lon": -43.1145}, {"type": "node", "id": 7413931780, "lat": -14.2460046, "lon": -43.1185964}, {"type": "node", "id": 7413937697, "lat": -14.2457811, "lon": -43.115715}, {"type": "node", "id": 7413937719, "lat": -14.2470398, "lon": -43.1318991}, {"type": "node", "id": 7413937722, "lat": -14.2470655, "lon": -43.1322346}, {"type": "node", "id": 7413937752, "lat": -14.2473222, "lon": -43.135364}, {"type": "node", "id": 7432575895, "lat": -14.2590566, "lon": -43.280126}, {"type": "node", "id": 7432575896, "lat": -14.2592184, "lon": -43.2820076}, {"type": "node", "id": 7432575897, "lat": -14.2595336, "lon": -43.2858525}, {"type": "node", "id": 7432575898, "lat": -14.2597224, "lon": -43.2882202}, {"type": "node", "id": 7432575899, "lat": -14.2598813, "lon": -43.2900881}, {"type": "node", "id": 7432575900, "lat": -14.260101, "lon": -43.2928061}, {"type": "node", "id": 7432575901, "lat": -14.2603197, "lon": -43.2954441}, {"type": "node", "id": 7432575902, "lat": -14.260463, "lon": -43.297213}, {"type": "node", "id": 7432575903, "lat": -14.2605891, "lon": -43.2987405}, {"type": "node", "id": 7432575904, "lat": -14.2606956, "lon": -43.2999931}, {"type": "node", "id": 7432575905, "lat": -14.2609868, "lon": -43.3034948}, {"type": "node", "id": 7432575906, "lat": -14.2610895, "lon": -43.30475}, {"type": "node", "id": 7432575907, "lat": -14.2612078, "lon": -43.3061528}, {"type": "node", "id": 7432575908, "lat": -14.2613429, "lon": -43.3077447}, {"type": "node", "id": 7432575909, "lat": -14.2615197, "lon": -43.3099052}, {"type": "node", "id": 7432575910, "lat": -14.2617628, "lon": -43.3127779}, {"type": "node", "id": 7432575911, "lat": -14.2620786, "lon": -43.3165853}, {"type": "node", "id": 7432575912, "lat": -14.2623035, "lon": -43.3192601}, {"type": "node", "id": 7432575913, "lat": -14.2624815, "lon": -43.3214501}, {"type": "node", "id": 7432575914, "lat": -14.2627194, "lon": -43.3243114}, {"type": "node", "id": 7432575915, "lat": -14.2626473, "lon": -43.3234209}, {"type": "node", "id": 7432575916, "lat": -14.2628289, "lon": -43.3255723}, {"type": "node", "id": 7432575917, "lat": -14.2629134, "lon": -43.3265822}, {"type": "node", "id": 7432575918, "lat": -14.2630102, "lon": -43.327747}, {"type": "node", "id": 7432575919, "lat": -14.26311, "lon": -43.3289821}, {"type": "node", "id": 7432575920, "lat": -14.2631961, "lon": -43.3299551}, {"type": "node", "id": 7432575921, "lat": -14.2632724, "lon": -43.3308908}, {"type": "node", "id": 7432575922, "lat": -14.2634164, "lon": -43.3325914}, {"type": "node", "id": 7432575923, "lat": -14.2635545, "lon": -43.33431}, {"type": "node", "id": 7432575924, "lat": -14.2636754, "lon": -43.3357637}, {"type": "node", "id": 7432824378, "lat": -14.2627393, "lon": -43.3245405}, {"type": "node", "id": 7432846931, "lat": -14.2605681, "lon": -43.298486}, {"type": "node", "id": 7432846953, "lat": -14.2606074, "lon": -43.298956}, {"type": "node", "id": 7433021163, "lat": -14.2597991, "lon": -43.2891215}, {"type": "node", "id": 7433137844, "lat": -14.2590914, "lon": -43.2805302}, {"type": "node", "id": 7433169605, "lat": -14.2590495, "lon": -43.2800399}, {"type": "node", "id": 7433169625, "lat": -14.2590843, "lon": -43.2804477}, {"type": "node", "id": 7551063015, "lat": -14.26476, "lon": -43.3489032}, {"type": "node", "id": 7551063016, "lat": -14.2647951, "lon": -43.349331}, {"type": "node", "id": 7551063017, "lat": -14.2648679, "lon": -43.3502001}, {"type": "node", "id": 7551063018, "lat": -14.2649056, "lon": -43.3506788}, {"type": "node", "id": 7551063019, "lat": -14.2649511, "lon": -43.3512247}, {"type": "node", "id": 7551063020, "lat": -14.2649992, "lon": -43.351808}, {"type": "node", "id": 7551063021, "lat": -14.2650551, "lon": -43.3524062}, {"type": "node", "id": 7551063022, "lat": -14.2651122, "lon": -43.3530875}, {"type": "node", "id": 7551063023, "lat": -14.265159, "lon": -43.3537151}, {"type": "node", "id": 7551063024, "lat": -14.2652331, "lon": -43.3545868}, {"type": "node", "id": 7551063025, "lat": -14.2652721, "lon": -43.3550374}, {"type": "node", "id": 7551063026, "lat": -14.265328, "lon": -43.3557133}, {"type": "node", "id": 7551063027, "lat": -14.2653904, "lon": -43.3563638}, {"type": "node", "id": 7551063028, "lat": -14.2654612, "lon": -43.3571047}, {"type": "node", "id": 7551063029, "lat": -14.2654944, "lon": -43.3574903}, {"type": "node", "id": 7551063030, "lat": -14.2655223, "lon": -43.3578692}, {"type": "node", "id": 7551063031, "lat": -14.2655548, "lon": -43.3582567}, {"type": "node", "id": 7551063032, "lat": -14.2655984, "lon": -43.358763}, {"type": "node", "id": 7551063033, "lat": -14.2656542, "lon": -43.3594094}, {"type": "node", "id": 7551063034, "lat": -14.2657075, "lon": -43.3600867}, {"type": "node", "id": 7551063035, "lat": -14.2657582, "lon": -43.3607183}, {"type": "node", "id": 7551063036, "lat": -14.2657946, "lon": -43.3611529}, {"type": "node", "id": 7551063037, "lat": -14.2658232, "lon": -43.3616866}, {"type": "node", "id": 7551063038, "lat": -14.2658596, "lon": -43.3621573}, {"type": "node", "id": 7551063039, "lat": -14.2658973, "lon": -43.3627099}, {"type": "node", "id": 7551063040, "lat": -14.265948, "lon": -43.3632624}, {"type": "node", "id": 7551063041, "lat": -14.2659883, "lon": -43.3636782}, {"type": "node", "id": 7551063042, "lat": -14.2660312, "lon": -43.3641368}, {"type": "node", "id": 7551063043, "lat": -14.2660767, "lon": -43.364637}, {"type": "node", "id": 7551063044, "lat": -14.266117, "lon": -43.3652741}, {"type": "node", "id": 7551063045, "lat": -14.2661741, "lon": -43.365952}, {"type": "node", "id": 7551063046, "lat": -14.2662287, "lon": -43.3666956}, {"type": "node", "id": 7551063047, "lat": -14.2662729, "lon": -43.367283}, {"type": "node", "id": 7551063048, "lat": -14.2663275, "lon": -43.3678155}, {"type": "node", "id": 7551063049, "lat": -14.2663769, "lon": -43.3683077}, {"type": "node", "id": 7551063050, "lat": -14.2664172, "lon": -43.368773}, {"type": "node", "id": 7551063051, "lat": -14.2664861, "lon": -43.3696997}, {"type": "node", "id": 7551063052, "lat": -14.2665303, "lon": -43.3701758}, {"type": "node", "id": 7551063053, "lat": -14.2665836, "lon": -43.3708128}, {"type": "node", "id": 7551063054, "lat": -14.2665602, "lon": -43.370546}, {"type": "node", "id": 7551063055, "lat": -14.2666083, "lon": -43.3710676}, {"type": "node", "id": 7551063056, "lat": -14.2666343, "lon": -43.3714941}, {"type": "node", "id": 7551063057, "lat": -14.2666628, "lon": -43.371883}, {"type": "node", "id": 7551063058, "lat": -14.2666927, "lon": -43.3722143}, {"type": "node", "id": 7551063059, "lat": -14.2667408, "lon": -43.3726662}, {"type": "node", "id": 7551063060, "lat": -14.2667863, "lon": -43.3732416}, {"type": "node", "id": 7551063061, "lat": -14.2668136, "lon": -43.3735688}, {"type": "node", "id": 7551063062, "lat": -14.26685, "lon": -43.3740154}, {"type": "node", "id": 7551063063, "lat": -14.2668812, "lon": -43.3743949}, {"type": "node", "id": 7551063064, "lat": -14.2669202, "lon": -43.3748643}, {"type": "node", "id": 7551063065, "lat": -14.2669658, "lon": -43.3754196}, {"type": "node", "id": 7551063066, "lat": -14.2669675, "lon": -43.3754465}, {"type": "node", "id": 7551063067, "lat": -14.2669995, "lon": -43.3758473}, {"type": "node", "id": 7551063068, "lat": -14.2670216, "lon": -43.3761746}, {"type": "node", "id": 7551063069, "lat": -14.2670567, "lon": -43.3766198}, {"type": "node", "id": 7551063070, "lat": -14.2670957, "lon": -43.3770517}, {"type": "node", "id": 7551063071, "lat": -14.2671308, "lon": -43.3774245}, {"type": "node", "id": 7551063072, "lat": -14.2671762, "lon": -43.3779086}, {"type": "node", "id": 7551063073, "lat": -14.2672074, "lon": -43.3782868}, {"type": "node", "id": 7551063074, "lat": -14.2672373, "lon": -43.3786502}, {"type": "node", "id": 7551063075, "lat": -14.2672854, "lon": -43.379074}, {"type": "node", "id": 7551063076, "lat": -14.2673218, "lon": -43.3795756}, {"type": "node", "id": 7551063077, "lat": -14.2673621, "lon": -43.3801402}, {"type": "node", "id": 7551063078, "lat": -14.2674011, "lon": -43.3806391}, {"type": "node", "id": 7551063079, "lat": -14.2674479, "lon": -43.3812252}, {"type": "node", "id": 7551063080, "lat": -14.2674869, "lon": -43.3817603}, {"type": "node", "id": 7551063081, "lat": -14.2675324, "lon": -43.382396}, {"type": "node", "id": 7551063082, "lat": -14.2675779, "lon": -43.3828814}, {"type": "node", "id": 7551063083, "lat": -14.2676299, "lon": -43.383446}, {"type": "node", "id": 7551063084, "lat": -14.2677156, "lon": -43.3843929}, {"type": "node", "id": 7551111785, "lat": -14.267817, "lon": -43.3856455}, {"type": "node", "id": 7551111786, "lat": -14.2678599, "lon": -43.3861484}, {"type": "node", "id": 7551111787, "lat": -14.2679015, "lon": -43.3866258}, {"type": "node", "id": 7551111788, "lat": -14.267934, "lon": -43.3870308}, {"type": "node", "id": 7551111789, "lat": -14.2679613, "lon": -43.3874466}, {"type": "node", "id": 7551111790, "lat": -14.2680029, "lon": -43.3879803}, {"type": "node", "id": 7551111791, "lat": -14.2680536, "lon": -43.3885328}, {"type": "node", "id": 7551111792, "lat": -14.2681212, "lon": -43.3892289}, {"type": "node", "id": 7551111793, "lat": -14.2682875, "lon": -43.3913063}, {"type": "node", "id": 7551111794, "lat": -14.2681783, "lon": -43.3899236}, {"type": "node", "id": 7551111795, "lat": -14.268255, "lon": -43.3908744}, {"type": "node", "id": 7551111796, "lat": -14.2647119, "lon": -43.3482608}, {"type": "node", "id": 7551111797, "lat": -14.2646768, "lon": -43.3478545}, {"type": "node", "id": 7551111798, "lat": -14.2646183, "lon": -43.3471209}, {"type": "node", "id": 7551111799, "lat": -14.2645521, "lon": -43.3463712}, {"type": "node", "id": 7551111800, "lat": -14.2644884, "lon": -43.3456001}, {"type": "node", "id": 7551111801, "lat": -14.2644143, "lon": -43.3447377}, {"type": "node", "id": 7551111802, "lat": -14.2643519, "lon": -43.3439975}, {"type": "node", "id": 7551111803, "lat": -14.2642999, "lon": -43.3433309}, {"type": "node", "id": 7551111804, "lat": -14.2642401, "lon": -43.3426403}, {"type": "node", "id": 7551111805, "lat": -14.2641868, "lon": -43.3419818}, {"type": "node", "id": 7551111806, "lat": -14.2641296, "lon": -43.3412683}, {"type": "node", "id": 7551111807, "lat": -14.264075, "lon": -43.3406152}, {"type": "node", "id": 7551111808, "lat": -14.2640231, "lon": -43.3399647}, {"type": "node", "id": 7551111809, "lat": -14.263988, "lon": -43.3395128}, {"type": "node", "id": 7551111810, "lat": -14.2639061, "lon": -43.3385982}, {"type": "node", "id": 7551111811, "lat": -14.2638541, "lon": -43.3379786}, {"type": "node", "id": 7551111812, "lat": -14.2638073, "lon": -43.3373362}, {"type": "node", "id": 7551111813, "lat": -14.2637423, "lon": -43.3365731}, {"type": "node", "id": 7551176701, "lat": -14.265218, "lon": -43.3544093}, {"type": "node", "id": 7551185551, "lat": -14.2652438, "lon": -43.3547098}, {"type": "node", "id": 7628107228, "lat": -14.2485463, "lon": -43.1507881}, {"type": "node", "id": 7628107237, "lat": -14.2485781, "lon": -43.1512032}, {"type": "node", "id": 7628107249, "lat": -14.2489024, "lon": -43.1552182}, {"type": "node", "id": 7628107250, "lat": -14.2487868, "lon": -43.1537269}, {"type": "node", "id": 7628376116, "lat": -14.2478782, "lon": -43.1422953}, {"type": "node", "id": 7628376117, "lat": -14.2484098, "lon": -43.1490652}, {"type": "node", "id": 7628376118, "lat": -14.2486828, "lon": -43.1523456}, {"type": "node", "id": 7628376119, "lat": -14.2489596, "lon": -43.1559049}, {"type": "node", "id": 7628376120, "lat": -14.249269, "lon": -43.159672}, {"type": "node", "id": 7628376121, "lat": -14.249581, "lon": -43.1635827}, {"type": "node", "id": 7628376122, "lat": -14.2497889, "lon": -43.1662542}, {"type": "node", "id": 7628515165, "lat": -14.2500068, "lon": -43.1688431}, {"type": "node", "id": 7628515166, "lat": -14.2499667, "lon": -43.1683193}, {"type": "node", "id": 7628515172, "lat": -14.2501438, "lon": -43.1686454}, {"type": "node", "id": 7628515176, "lat": -14.2499895, "lon": -43.1685652}, {"type": "node", "id": 7628640803, "lat": -14.2491949, "lon": -43.157077}, {"type": "node", "id": 7628640804, "lat": -14.2491468, "lon": -43.1571487}, {"type": "node", "id": 7628640805, "lat": -14.2492131, "lon": -43.1568383}, {"type": "node", "id": 7628640806, "lat": -14.2490669, "lon": -43.1567008}, {"type": "node", "id": 7628640807, "lat": -14.2491299, "lon": -43.1567658}, {"type": "node", "id": 7628640808, "lat": -14.2491728, "lon": -43.1568074}, {"type": "node", "id": 7628640809, "lat": -14.2492741, "lon": -43.1568821}, {"type": "node", "id": 7628640810, "lat": -14.2490015, "lon": -43.1565916}, {"type": "node", "id": 7628640811, "lat": -14.2492885, "lon": -43.1569471}, {"type": "node", "id": 7628640812, "lat": -14.2490587, "lon": -43.1573264}, {"type": "node", "id": 7628640820, "lat": -14.2500931, "lon": -43.1684496}, {"type": "node", "id": 7628640821, "lat": -14.2500515, "lon": -43.16842}, {"type": "node", "id": 7628640822, "lat": -14.2501412, "lon": -43.1684683}, {"type": "node", "id": 7628640823, "lat": -14.2502101, "lon": -43.1684804}, {"type": "node", "id": 7628640824, "lat": -14.2502233, "lon": -43.1685864}, {"type": "node", "id": 7628640825, "lat": -14.250071, "lon": -43.1687567}, {"type": "node", "id": 7628798291, "lat": -14.2493364, "lon": -43.1605294}, {"type": "node", "id": 7628798295, "lat": -14.2492999, "lon": -43.1600651}, {"type": "node", "id": 7946270883, "lat": -14.2499589, "lon": -43.1682522}, {"type": "node", "id": 8408542362, "lat": -14.2547068, "lon": -43.2275396}, {"type": "node", "id": 8444464461, "lat": -14.2514549, "lon": -43.1834039}, {"type": "node", "id": 8444464462, "lat": -14.251247, "lon": -43.1837934}, {"type": "node", "id": 8653608307, "lat": -14.2433189, "lon": -43.0858069}, {"type": "node", "id": 8653641423, "lat": -14.2433039, "lon": -43.0856191}, {"type": "node", "id": 9730045507, "lat": -14.2524279, "lon": -43.1990354}, {"type": "node", "id": 9730185528, "lat": -14.2490317, "lon": -43.15698}, {"type": "node", "id": 10078007371, "lat": -14.2727976, "lon": -43.4445977}, {"type": "node", "id": 11595846617, "lat": -14.240757, "lon": -43.0536448}, {"type": "node", "id": 11595846626, "lat": -14.2403109, "lon": -43.0480179}, {"type": "node", "id": 11595846642, "lat": -14.2402324, "lon": -43.0470276}, {"type": "node", "id": 12417342764, "lat": -14.2502118, "lon": -43.1713241}, {"type": "node", "id": 12542765098, "lat": -14.2494096, "lon": -43.1614543}, {"type": "node", "id": 12560253815, "lat": -14.2495468, "lon": -43.1631574}, {"type": "node", "id": 12626250304, "lat": -14.2487657, "lon": -43.1534692}, {"type": "node", "id": 12638507077, "lat": -14.2570315, "lon": -43.2554215}, {"type": "node", "id": 12638507078, "lat": -14.2570939, "lon": -43.2561672}, {"type": "node", "id": 12638507079, "lat": -14.2572187, "lon": -43.2578141}, {"type": "node", "id": 12638507080, "lat": -14.2574839, "lon": -43.2610059}, {"type": "node", "id": 12638507081, "lat": -14.258009, "lon": -43.2673252}, {"type": "node", "id": 12659369898, "lat": -14.2466118, "lon": -43.1260822}, {"type": "way", "id": 280706051, "nodes": [3898730504, 3898730503, 1832311428, 3898730502, 353133312, 3422099004, 3898730501, 353133313, 3898730500, 10078007371, 4347894225, 4347911896, 3898730499, 353133308, 3422098997], "tags": {"IBGE:CD_ADMINIS": "federal", "addr:county": "Iui\u00fa", "highway": "primary", "lanes": "2", "maxspeed": "80", "ref": "BR-030", "source": "IBGE,bing", "surface": "asphalt"}}, {"type": "way", "id": 335084617, "nodes": [3422098997, 3422098996, 7551111793, 7551111795, 7551111794, 7551111792, 7551111791, 7551111790, 7551111789, 7551111788, 7551111787, 7551111786, 7551111785, 7551063084, 7551063083, 7551063082, 7551063081, 7551063080, 7551063079, 7551063078, 7551063077, 7551063076, 7551063075, 7551063074, 7551063073, 7551063072, 7551063071, 7551063070, 7551063069, 7551063068, 7551063067, 7551063066, 7551063065, 7551063064, 7551063063, 7551063062, 7551063061, 7551063060, 7551063059, 7551063058, 7551063057, 7551063056, 7551063055, 7551063053, 7551063054, 7551063052, 7551063051, 353133309, 7551063050, 7551063049, 7551063048, 7551063047, 7551063046, 7551063045, 7551063044, 7551063043, 7551063042, 7551063041, 7551063040, 7551063039, 7551063038, 7551063037, 7551063036, 7551063035, 7551063034, 7551063033, 7551063032, 7551063031, 7551063030, 7551063029, 7551063028, 7551063027, 7551063026, 7551063025, 7551185551, 7551063024, 7551176701, 7551063023, 7551063022, 7551063021, 7551063020, 7551063019, 7551063018, 7551063017, 7551063016, 7551063015, 353133310], "tags": {"IBGE:CD_ADMINIS": "federal", "addr:county": "Palmas de Monte Alto", "highway": "primary", "maxspeed": "80", "ref": "BR-030", "source": "IBGE,bing"}}, {"type": "way", "id": 482698582, "nodes": [8408542362, 353133301, 12638507077, 12638507078, 12638507079, 12638507080, 12638507081, 7433169605, 7432575895, 7433169625, 7433137844, 7432575896, 7432575897, 7432575898, 7433021163, 7432575899, 7432575900, 7058120457, 4279268546, 7432575901, 7432575902, 7432846931, 7432575903, 7432846953, 7432575904, 3843059959, 7432575905, 7432575906, 7432575907, 7432575908, 7432575909, 7432575910, 7432575911, 7432575912, 7432575913, 7432575915, 7432575914, 7432824378, 7432575916, 7432575917, 7432575918, 7432575919, 7432575920, 7432575921, 7432575922, 7432575923, 7432575924, 7551111813, 7551111812, 7551111811, 7551111810, 7551111809, 7551111808, 7551111807, 7551111806, 7551111805, 7551111804, 7551111803, 7551111802, 7551111801, 7551111800, 7551111799, 7551111798, 7551111797, 7551111796, 353133310], "tags": {"IBGE:CD_ADMINIS": "federal", "addr:county": "Palmas de Monte Alto", "highway": "primary", "maxspeed": "80", "oneway": "no", "ref": "BR-030", "source": "IBGE,bing", "surface": "asphalt"}}, {"type": "way", "id": 562374558, "nodes": [6026120393, 8444464462, 5421685942, 5421685941, 5421685911], "tags": {"highway": "primary_link", "maxspeed": "40", "oneway": "yes", "surface": "asphalt"}}, {"type": "way", "id": 639531430, "nodes": [8444464461, 5421685930, 5421685931, 5421685932, 6026120392], "tags": {"highway": "primary_link", "maxspeed": "40", "oneway": "yes", "surface": "asphalt"}}, {"type": "way", "id": 816782554, "nodes": [7628515165, 7628640825, 7628515172, 7628640824], "tags": {"highway": "primary_link", "maxspeed": "40", "oneway": "yes"}}, {"type": "way", "id": 816782555, "nodes": [7628640823, 7628640822, 7628640820, 7628640821, 7628515166], "tags": {"highway": "primary_link", "maxspeed": "40", "oneway": "yes"}}, {"type": "way", "id": 816791728, "nodes": [7628640809, 7628640805, 7628640808, 7628640807, 7628640806, 7628640810], "tags": {"highway": "primary_link", "maxspeed": "40", "oneway": "yes", "surface": "asphalt"}}, {"type": "way", "id": 816791729, "nodes": [7628640812, 7628640804, 7628640803, 7628640811], "tags": {"highway": "primary_link", "maxspeed": "40", "oneway": "yes", "surface": "asphalt"}}, {"type": "way", "id": 816791730, "nodes": [7628640810, 9730185528], "tags": {"IBGE:CD_ADMINIS": "federal", "addr:county": "Palmas de Monte Alto", "highway": "primary", "maxspeed": "40", "oneway": "no", "ref": "BR-030", "source": "IBGE,bing", "surface": "asphalt"}}, {"type": "way", "id": 816791731, "nodes": [9730185528, 7628640812], "tags": {"IBGE:CD_ADMINIS": "federal", "addr:county": "Palmas de Monte Alto", "highway": "primary", "maxspeed": "40", "oneway": "no", "ref": "BR-030", "source": "IBGE,bing", "surface": "asphalt"}}, {"type": "way", "id": 851941546, "nodes": [7628515176, 7628515165], "tags": {"IBGE:CD_ADMINIS": "federal", "addr:county": "Palmas de Monte Alto", "highway": "primary", "maxspeed": "40", "oneway": "no", "ref": "BR-030", "source": "IBGE,bing", "surface": "asphalt"}}, {"type": "way", "id": 851941547, "nodes": [7628515166, 7628515176], "tags": {"IBGE:CD_ADMINIS": "federal", "addr:county": "Palmas de Monte Alto", "highway": "primary", "maxspeed": "40", "oneway": "no", "ref": "BR-030", "source": "IBGE,bing", "surface": "asphalt"}}, {"type": "way", "id": 851941548, "nodes": [4755001550, 11595846642, 4755001658, 11595846626, 4755001627, 4755001628, 11595846617, 1832311426, 4755001613, 4755001612, 8653641423, 8653608307, 353133289, 353133292, 353133293, 7413931779, 7413900024, 7413937697, 7413900025, 7413931780, 353133456, 7413900026, 12659369898, 353133295, 7413900027, 7413900028, 7413895563, 7413900029, 5607512530, 7284051913, 5607510601, 5607510593, 7413937719, 5607510590, 7413937722, 5607510568, 7413895583, 7413895580, 7413937752, 353133294, 7413895584, 7413900023, 7413900030, 7413900031, 7628376116, 353133297, 353133296, 5622142129], "tags": {"IBGE:CD_ADMINIS": "federal", "addr:county": "Palmas de Monte Alto", "highway": "primary", "maxspeed": "80", "oneway": "no", "ref": "BR-030", "source": "IBGE,bing", "surface": "asphalt"}}, {"type": "way", "id": 1058928097, "nodes": [2389811650, 5586095904, 353133302, 5586095905, 5421685939, 6026120392], "tags": {"IBGE:CD_ADMINIS": "federal", "addr:county": "Palmas de Monte Alto", "highway": "primary", "maxspeed": "80", "oneway": "no", "ref": "BR-030", "source": "IBGE,bing", "surface": "asphalt"}}, {"type": "way", "id": 1058930767, "nodes": [6026120393, 5421685947, 5586095826, 9730045507, 1832311427, 8408542362], "tags": {"IBGE:CD_ADMINIS": "federal", "addr:county": "Palmas de Monte Alto", "highway": "primary", "maxspeed": "80", "oneway": "no", "ref": "BR-030", "source": "IBGE,bing", "surface": "asphalt"}}, {"type": "way", "id": 1058930768, "nodes": [5421685914, 6026120393], "tags": {"IBGE:CD_ADMINIS": "federal", "addr:county": "Palmas de Monte Alto", "highway": "primary", "maxspeed": "40", "oneway": "no", "ref": "BR-030", "source": "IBGE,bing", "surface": "asphalt"}}, {"type": "way", "id": 1058930769, "nodes": [5421685915, 5421685914], "tags": {"IBGE:CD_ADMINIS": "federal", "addr:county": "Palmas de Monte Alto", "highway": "primary", "maxspeed": "80", "oneway": "no", "ref": "BR-030", "source": "IBGE,bing", "surface": "asphalt"}}, {"type": "way", "id": 1058930770, "nodes": [6026120392, 5421685915], "tags": {"IBGE:CD_ADMINIS": "federal", "addr:county": "Palmas de Monte Alto", "highway": "primary", "maxspeed": "40", "oneway": "no", "ref": "BR-030", "source": "IBGE,bing", "surface": "asphalt"}}, {"type": "way", "id": 1058940643, "nodes": [5622142129, 7628376117, 7628107228, 7628107237, 7628376118, 12626250304, 7628107250, 7628107249, 7628376119, 7628640810], "tags": {"IBGE:CD_ADMINIS": "federal", "addr:county": "Palmas de Monte Alto", "highway": "primary", "maxspeed": "80", "oneway": "no", "ref": "BR-030", "source": "IBGE,bing", "surface": "asphalt"}}, {"type": "way", "id": 1058940644, "nodes": [7628640812, 353133300, 7628376120, 7628798295, 7628798291, 2389842672, 12542765098, 12560253815, 7628376121, 7628376122], "tags": {"IBGE:CD_ADMINIS": "federal", "addr:county": "Palmas de Monte Alto", "highway": "primary", "maxspeed": "80", "oneway": "no", "ref": "BR-030", "source": "IBGE,bing", "surface": "asphalt"}}, {"type": "way", "id": 1383561743, "nodes": [7628376122, 2389814815, 7946270883, 7628515166], "tags": {"IBGE:CD_ADMINIS": "federal", "addr:county": "Palmas de Monte Alto", "highway": "primary", "maxspeed": "80", "oneway": "no", "postal_code": "46466-075", "ref": "BR-030", "source": "IBGE,bing", "surface": "asphalt"}}, {"type": "way", "id": 1383561744, "nodes": [7628515165, 5602264289, 2389639962, 12417342764, 2389644883, 2389642687, 2389811650], "tags": {"IBGE:CD_ADMINIS": "federal", "addr:county": "Palmas de Monte Alto", "highway": "primary", "maxspeed": "80", "oneway": "no", "postal_code": "46465-840", "ref": "BR-030", "source": "IBGE,bing", "surface": "asphalt"}}]}